Metadata-Version: 1.1
Name: wordnet
Version: 0.0.1b2
Summary: An module to create network of words on bases of realtive sense under a corpus of document.
Home-page: https://anuragkumarak95.github.io/wordnet/
Author: Anurag Kumar
Author-email: anuragkumarak95@gmail.com
License: GNU General Public License v3
Keywords: word network python twitter streaming data
Platform: UNKNOWN
Classifier: Development Status :: 4 - Beta
Classifier: Topic :: Utilities
Classifier: License :: OSI Approved :: GNU General Public License v3 (GPLv3)
Classifier: Programming Language :: Python
